directize/__init__.py
directize/basic.py
directize/config.py
directize/directize.py
directize/monorepo.py
directize/standard.py
directize/utils.py
directize-0.0.6.dist-info/LICENSE
directize-0.0.6.dist-info/METADATA
directize-0.0.6.dist-info/WHEEL
directize-0.0.6.dist-info/top_level.txt
directize-0.0.6.dist-info/RECORD
