Metadata-Version: 2.1
Name: directize
Version: 0.0.6
Summary: a tool to help you manage your AI/DS projects
Home-page: https://github.com/Allaye/directize
Author: Kolade Gideon (Allaye)
Author-email: allaye@allaye.com
License: UNKNOWN
Project-URL: Bug Tracker, https://github.com/Allaye/directize/issues
Platform: UNKNOWN
Classifier: Programming Language :: Python :: 3
Classifier: License :: OSI Approved :: MIT License
Classifier: Operating System :: OS Independent
Requires-Python: >=3.7
License-File: LICENSE
